{
  "document_id": "178.1",
  "assessed_at": "2025-12-29T11:32:34.513052",
  "input_files": {
    "entities": "data/ocr_text/178.1_ocr_cleaned_entities.json",
    "classification": "data/ocr_text/178.1_ocr_cleaned_classification.json"
  },
  "classification_summary": {
    "label": "Loan Detected",
    "confidence": 0.818
  },
  "entity_summary": {
    "survey_numbers_found": 2,
    "dates_found": 0,
    "banks_found": 1,
    "loan_present": true,
    "case_numbers_found": 0,
    "persons_found": 0,
    "organizations_found": 0
  },
  "risk_assessment": {
    "risk_score": 35,
    "risk_level": "Medium",
    "risk_percentage": "35%",
    "factors": [
      "Loan/Encumbrance detected (Amount: 200000/-) (30 points)",
      "No dates found (5 points)"
    ],
    "flags": [
      "LOAN_PRESENT",
      "NO_DATES"
    ],
    "explanation": "Risk Score: 35/100 (Medium Risk) - Loan/Encumbrance detected (Amount: 200000/-) (30 points) | No dates found (5 points)",
    "recommendations": [
      "⚠️ PROCEED WITH CAUTION",
      "Obtain legal opinion before finalizing transaction",
      "Obtain No Objection Certificate (NOC) from all lenders",
      "Verify loan status and outstanding amount",
      "Verify seller's identity and ownership chain",
      "Conduct site inspection",
      "Obtain updated Encumbrance Certificate"
    ],
    "breakdown": {
      "loan_risk": 30,
      "legal_risk": 0,
      "mutation_risk": 0,
      "data_quality_risk": 0,
      "other_risks": 5
    },
    "summary": "⚠️ Document requires additional legal review before proceeding"
  }
}